AUTHORS
ChangeLog
LICENSE
README.rst
requirements.txt
setup.cfg
setup.py
src/fs_manager/__init__.py
src/fs_manager/fs_manager.py
src/fs_manager/logger.py
src/fs_manager.egg-info/PKG-INFO
src/fs_manager.egg-info/SOURCES.txt
src/fs_manager.egg-info/dependency_links.txt
src/fs_manager.egg-info/not-zip-safe
src/fs_manager.egg-info/pbr.json
src/fs_manager.egg-info/requires.txt
src/fs_manager.egg-info/top_level.txt
src/fs_manager/tests/test_directory_and_file.py
src/fs_manager/tests/test_directory_object.py
src/fs_manager/tests/test_file_object.py
src/fs_manager/tests/test_fs_manager.py