Metadata-Version: 1.1
Name: fs-manager
Version: 0.3.0
Summary: This module is designed to relief and simplify interaction of your python modules with the file system.
Home-page: https://github.com/FromZeus/fs-manager
Author: 
Author-email: 
License: UNKNOWN
Platform: UNKNOWN
Classifier: Intended Audience :: Information Technology
Classifier: Intended Audience :: System Administrators
Classifier: License :: OSI Approved :: Apache Software License
Classifier: Operating System :: POSIX :: Linux
Classifier: Programming Language :: Python
Classifier: Programming Language :: Python :: 2
Classifier: Programming Language :: Python :: 2.7
Classifier: Programming Language :: Python :: 3
Classifier: Programming Language :: Python :: 3.4
